orlab/__init__.py
orlab/_enums.py
orlab/_orhelper.py
orlab/core/__init__.py
orlab/core/helper.py
orlab/core/jiterator.py
orlab/core/openrocket_instance.py
orlab/core/simulation_listener.py
orlab/utils/__init__.py
orlab/utils/utils.py
orlab-0.2.7.dist-info/LICENSE
orlab-0.2.7.dist-info/METADATA
orlab-0.2.7.dist-info/WHEEL
orlab-0.2.7.dist-info/top_level.txt
orlab-0.2.7.dist-info/RECORD
