Metadata-Version: 2.1
Name: orlab
Version: 0.2.7
Summary: OrLab is a Python module designed for interacting and scripting with OpenRocket, with enhanced capabilities for simulations and computational workflows.
Home-page: https://github.com/CameronBrooks11/orlab
Author: Cameron Brooks
Author-email: cambrooks3393@gmail.com
Requires-Python: >=3.6
License-File: LICENSE
Requires-Dist: jpype1>=0.6.3
Requires-Dist: numpy
